base128/__init__.py
base128/base128.py
base128-0.1.1.dist-info/DESCRIPTION.rst
base128-0.1.1.dist-info/METADATA
base128-0.1.1.dist-info/RECORD
base128-0.1.1.dist-info/WHEEL
base128-0.1.1.dist-info/entry_points.txt
base128-0.1.1.dist-info/metadata.json
base128-0.1.1.dist-info/top_level.txt
