Metadata-Version: 2.0
Name: base128
Version: 0.1.1
Summary: Encodes to and decodes from base128.
Home-page: https://github.com/rpuntaie/base128
Author: Roland Puntaier
Author-email: roland.puntaier@gmail.com
License: MIT
Keywords: encoding, base128, iso-8859
Platform: UNKNOWN
Classifier: Development Status :: 3 - Alpha
Classifier: Topic :: Software Development
Classifier: Intended Audience :: Education
Classifier: License :: OSI Approved :: MIT License
Classifier: Operating System :: POSIX :: Linux
Classifier: Programming Language :: Python :: 3 :: Only
Requires-Python: >3.3
Requires-Dist: bitarray (>=0.8.1)
